differometor/__init__.py
differometor/build.py
differometor/components.py
differometor/plot.py
differometor/setups.py
differometor/simulate.py
differometor/utils.py
differometor-0.0.2.dist-info/licenses/LICENSE
differometor-0.0.2.dist-info/METADATA
differometor-0.0.2.dist-info/WHEEL
differometor-0.0.2.dist-info/top_level.txt
differometor-0.0.2.dist-info/RECORD
