Metadata-Version: 2.4
Name: differometor
Version: 0.0.2
Summary: A Differentiable Interferometer Simulator for the Compuational Design of Gravitational Wave Detectors
Author-email: Artificial Scientist Lab <jonathan.klimesch@mpl.mpg.de>
License-Expression: MIT
Project-URL: Homepage, https://github.com/artificial-scientist-lab/Differometor
Project-URL: Issues, https://github.com/artificial-scientist-lab/Differometor/issues
Classifier: Programming Language :: Python :: 3
Classifier: Operating System :: OS Independent
Requires-Python: >=3.11
License-File: LICENSE
Requires-Dist: jax==0.5.0
Requires-Dist: optax==0.2.4
Requires-Dist: numpy
Requires-Dist: matplotlib
Requires-Dist: tqdm
Dynamic: license-file
